[
  {
    "name": "John Doe",
    "email": "john@email.com"
  },
  {
    "name": "Jane Doe",
    "email": "jane@email.com"
  },
  {
    "name": "Bob Smith",
    "email": "bob@email.com"
  },
  {
    "name": "Alice Johnson",
    "email": "alice@email.com"
  },
  {
    "name": "Mike Brown",
    "email": "mike@email.com"
  },
  {
    "name": "Emily Davis",
    "email": "emily@email.com"
  },
  {
    "name": "Sarah Taylor",
    "email": "sarah@email.com"
  },
  {
    "name": "Kevin White",
    "email": "kevin@email.com"
  },
  {
    "name": "Rebecca Lee",
    "email": "rebecca@email.com"
  },
  {
    "name": "Richard Martin",
    "email": "richard@email.com"
  },
  {
    "name": "Laura Harris",
    "email": "laura@email.com"
  },
  {
    "name": "Justin Hall",
    "email": "justin@email.com"
  },
  {
    "name": "Karen Watson",
    "email": "karen@email.com"
  },
  {
    "name": "Brian Jackson",
    "email": "brian@email.com"
  },
  {
    "name": "Diane Brooks",
    "email": "diane@email.com"
  },
  {
    "name": "Lisa Thompson",
    "email": "lisa@email.com"
  },
  {
    "name": "Michael Lewis",
    "email": "michael@email.com"
  },
  {
    "name": "Elizabeth Clark",
    "email": "elizabeth@email.com"
  },
  {
    "name": "David Miller",
    "email": "david@email.com"
  },
  {
    "name": "Heather King",
    "email": "heather@email.com"
  },
  {
    "name": "Paul Davis",
    "email": "paul@email.com"
  }
]
